firmatazero/__init__.py
firmatazero/output_devices.py
firmatazero/shared_board.py
firmatazero-0.0.2.dist-info/LICENSE
firmatazero-0.0.2.dist-info/WHEEL
firmatazero-0.0.2.dist-info/METADATA
firmatazero-0.0.2.dist-info/RECORD
