Metadata-Version: 2.1
Name: firmatazero
Version: 0.0.2
Summary: firmatazero
Keywords: firmatazero,arduino,gpiozero,firmata,pyFirmata2
Author: Olli Paloviita
Requires-Python: >=3.7
Classifier: Development Status :: 4 - Beta
Classifier: Intended Audience :: Developers
Classifier: Operating System :: MacOS
Classifier: Operating System :: Microsoft :: Windows
Classifier: Operating System :: POSIX :: BSD
Classifier: Operating System :: POSIX :: Linux
Classifier: Programming Language :: Python :: 3
Classifier: Topic :: Software Development :: Libraries :: Python Modules
Requires-Dist: pyFirmata2==2.4.2
Requires-Dist: pyserial==3.5
Requires-Dist: black==22.3.0 ; extra == "dev"
Requires-Dist: codespell==2.1.0 ; extra == "dev"
Requires-Dist: flake8==4.0.1 ; extra == "dev"
Requires-Dist: isort==5.9.3 ; extra == "dev"
Requires-Dist: pep8-naming==0.12.1 ; extra == "dev"
Requires-Dist: pre-commit==2.18.1 ; extra == "dev"
Requires-Dist: pyproject-flake8==0.0.1a2 ; extra == "dev"
Project-URL: Home, https://github.com/ollipal/firmatazero
Provides-Extra: dev
